dora_gen72/main.py
dora_gen72/robotic_arm_package/__init__.py
dora_gen72/robotic_arm_package/libs/linux_arm/libRM_Base.so.1.0.0
dora_gen72/robotic_arm_package/libs/linux_x86/libRM_Base.so.1.0.0
dora_gen72/robotic_arm_package/libs/win_32/RM_Base.dll
dora_gen72/robotic_arm_package/libs/win_64/RM_Base.dll
dora_gen72/robotic_arm_package/log_setting.py
dora_gen72/robotic_arm_package/robotic_arm.py
dora_gen72-0.2.3.dist-info/METADATA
dora_gen72-0.2.3.dist-info/WHEEL
dora_gen72-0.2.3.dist-info/entry_points.txt
dora_gen72-0.2.3.dist-info/RECORD
