Metadata-Version: 2.1
Name: dora-gen72
Version: 0.2.3
Summary: Dora Node client for gen72 robotic arms.
Author: dora-rs team
Requires-Python: >=3.9,<4.0
Classifier: Programming Language :: Python :: 3
Classifier: Programming Language :: Python :: 3.9
Classifier: Programming Language :: Python :: 3.10
Classifier: Programming Language :: Python :: 3.11
Requires-Dist: dora-rs (>=0.3.6,<0.4.0)
